<?xml version="1.0" encoding="utf-8"?>
<!DOCTYPE type>
<decorators defaultdir="/WEB-INF/view/decorator/">
    <!-- Any urls that are excluded will never be decorated by Sitemesh -->
    <excludes>
        <pattern>/admin</pattern>
        <pattern>/admin/</pattern>
        <pattern>/admin/login*</pattern>
        <pattern>/admin/attachment/save*</pattern>
        <pattern>/mobile/*</pattern>
        <pattern>/static/tiny_mce/*</pattern>
        <pattern>/robots.txt</pattern>
    </excludes>

    <decorator name="admin" page="admin.jsp">
        <pattern>/admin/*</pattern>
    </decorator>

    <decorator name="front" page="front.jsp">
        <pattern>/*</pattern>
    </decorator>
</decorators>
